.eslintrc.json
.gitlab-ci.yml
.prettierrc.json
.stylelintrc.json
.travis.yml
CHANGES.rst
CONTRIBUTORS.rst
DEVELOP.rst
LICENSE.GPL
LICENSE.rst
MANIFEST.in
README.rst
constraints.txt
constraints_plone52.txt
package.json
postcss.config.js
publiccode.yml
requirements.txt
setup.cfg
setup.py
webpack.config.js
yarn.lock
docs/MA_Plone5_uso_CustomerSatisfaction.pdf
docs/conf.py
docs/customer-satisfaction-global.png
docs/customer-satisfaction_1-Recensione.jpg
docs/customer-satisfaction_2-Elenco-Recensioni.jpg
docs/customer-satisfaction_3-Dettaglio-Commenti.jpg
docs/index.rst
src/rer/__init__.py
src/rer.customersatisfaction.egg-info/PKG-INFO
src/rer.customersatisfaction.egg-info/SOURCES.txt
src/rer.customersatisfaction.egg-info/dependency_links.txt
src/rer.customersatisfaction.egg-info/entry_points.txt
src/rer.customersatisfaction.egg-info/namespace_packages.txt
src/rer.customersatisfaction.egg-info/not-zip-safe
src/rer.customersatisfaction.egg-info/requires.txt
src/rer.customersatisfaction.egg-info/top_level.txt
src/rer/customersatisfaction/__init__.py
src/rer/customersatisfaction/configure.zcml
src/rer/customersatisfaction/contentrules.py
src/rer/customersatisfaction/contentrules.zcml
src/rer/customersatisfaction/events.py
src/rer/customersatisfaction/interfaces.py
src/rer/customersatisfaction/permissions.zcml
src/rer/customersatisfaction/setuphandlers.py
src/rer/customersatisfaction/testing.py
src/rer/customersatisfaction/upgrades.py
src/rer/customersatisfaction/upgrades.zcml
src/rer/customersatisfaction/browser/__init__.py
src/rer/customersatisfaction/browser/adapters.py
src/rer/customersatisfaction/browser/configure.zcml
src/rer/customersatisfaction/browser/customer_satisfaction.pt
src/rer/customersatisfaction/browser/customer_satisfaction.py
src/rer/customersatisfaction/browser/customer_satisfaction_global.pt
src/rer/customersatisfaction/browser/customer_satisfaction_global.py
src/rer/customersatisfaction/browser/customer_satisfaction_viewlet.pt
src/rer/customersatisfaction/browser/show_feedbacks.pt
src/rer/customersatisfaction/browser/show_feedbacks.py
src/rer/customersatisfaction/browser/viewlets.py
src/rer/customersatisfaction/browser/overrides/.gitkeep
src/rer/customersatisfaction/browser/static/rer-customersatisfaction.css
src/rer/customersatisfaction/browser/static/rer-customersatisfaction.js
src/rer/customersatisfaction/browser/static/apps/customer_satisfaction_global/src/App.css
