Metadata-Version: 2.1
Name: rer.customersatisfaction
Version: 2.2.6
Summary: Customer satisfaction
Home-page: https://github.com/collective/rer.customersatisfaction
Author: RedTurtle Technology
Author-email: sviluppo@redturtle.it
License: GPL version 2
Project-URL: PyPI, https://pypi.python.org/pypi/rer.customersatisfaction
Project-URL: Source, https://github.com/collective/rer.customersatisfaction
Project-URL: Tracker, https://github.com/collective/rer.customersatisfaction/issues
Keywords: Python Plone CMS
Platform: UNKNOWN
Classifier: Environment :: Web Environment
Classifier: Framework :: Plone
Classifier: Framework :: Plone :: Addon
Classifier: Framework :: Plone :: 5.1
Classifier: Framework :: Plone :: 5.2
Classifier: Programming Language :: Python
Classifier: Programming Language :: Python :: 2.7
Classifier: Programming Language :: Python :: 3.7
Classifier: Operating System :: OS Independent
Classifier: License :: OSI Approved :: GNU General Public License v2 (GPLv2)
Provides-Extra: test
